[
  {
    "title": "Ragnarok_L7",
    "link_thumb": "https://live.staticflickr.com/65535/51787984340_aeb670904a_o.gif",
    "id_album": "1601322215",
    "total": 15,
    "size_max_detail_page": 1,
    "list_detail": [
      {
        "index_page": 0,
        "link_page": "https://github.com/lmbstudiocontact/mb4_dt_alb_0/raw/main/14132021_dta_1601322215_index_0.json"
      }
    ]
  },
  {
    "title": "Marvel",
    "link_thumb": "https://live.staticflickr.com/65535/51787155533_fe5b0b8c73_o.gif",
    "id_album": "-1997428321",
    "total": 194,
    "size_max_detail_page": 4,
    "list_detail": [
      {
        "index_page": 0,
        "link_page": "https://github.com/lmbstudiocontact/mb4_dt_alb_0/raw/main/14132021_dta_-1997428321_index_0.json"
      },
      {
        "index_page": 1,
        "link_page": "https://github.com/lmbstudiocontact/mb4_dt_alb_0/raw/main/14132021_dta_-1997428321_index_1.json"
      },
      {
        "index_page": 2,
        "link_page": "https://github.com/lmbstudiocontact/mb4_dt_alb_0/raw/main/14132021_dta_-1997428321_index_2.json"
      },
      {
        "index_page": 3,
        "link_page": "https://github.com/lmbstudiocontact/mb4_dt_alb_0/raw/main/14132021_dta_-1997428321_index_3.json"
      }
    ]
  },
  {
    "title": "Halloween Ghost Witch_L3",
    "link_thumb": "https://live.staticflickr.com/65535/51787245833_96bcfa8ae8_o.gif",
    "id_album": "1746571235",
    "total": 49,
    "size_max_detail_page": 1,
    "list_detail": [
      {
        "index_page": 0,
        "link_page": "https://github.com/lmbstudiocontact/mb4_dt_alb_0/raw/main/14132021_dta_1746571235_index_0.json"
      }
    ]
  },
  {
    "title": "Kitty & My Melody_L1",
    "link_thumb": "https://live.staticflickr.com/65535/51786203482_195a5c4f42_o.gif",
    "id_album": "-378480545",
    "total": 76,
    "size_max_detail_page": 2,
    "list_detail": [
      {
        "index_page": 0,
        "link_page": "https://github.com/lmbstudiocontact/mb4_dt_alb_0/raw/main/14132021_dta_-378480545_index_0.json"
      },
      {
        "index_page": 1,
        "link_page": "https://github.com/lmbstudiocontact/mb4_dt_alb_0/raw/main/14132021_dta_-378480545_index_1.json"
      }
    ]
  },
  {
    "title": "Ghibli Anime_L8",
    "link_thumb": "https://live.staticflickr.com/65535/51787243948_c8d57ed911_o.gif",
    "id_album": "-749595040",
    "total": 17,
    "size_max_detail_page": 1,
    "list_detail": [
      {
        "index_page": 0,
        "link_page": "https://github.com/lmbstudiocontact/mb4_dt_alb_0/raw/main/14132021_dta_-749595040_index_0.json"
      }
    ]
  },
  {
    "title": "Rio 2_L7",
    "link_thumb": "https://live.staticflickr.com/65535/51787982125_d1161e2809_o.gif",
    "id_album": "-1210862912",
    "total": 17,
    "size_max_detail_page": 1,
    "list_detail": [
      {
        "index_page": 0,
        "link_page": "https://github.com/lmbstudiocontact/mb4_dt_alb_0/raw/main/14132021_dta_-1210862912_index_0.json"
      }
    ]
  },
  {
    "title": "Finn Mertens Cartoon",
    "link_thumb": "https://live.staticflickr.com/65535/51786074632_223722a716_o.gif",
    "id_album": "-1437374559",
    "total": 8,
    "size_max_detail_page": 1,
    "list_detail": [
      {
        "index_page": 0,
        "link_page": "https://github.com/lmbstudiocontact/mb4_dt_alb_0/raw/main/14132021_dta_-1437374559_index_0.json"
      }
    ]
  },
  {
    "title": "City",
    "link_thumb": "https://live.staticflickr.com/65535/51787772240_1c1d088491_o.gif",
    "id_album": "2100619",
    "total": 8,
    "size_max_detail_page": 1,
    "list_detail": [
      {
        "index_page": 0,
        "link_page": "https://github.com/lmbstudiocontact/mb4_dt_alb_0/raw/main/14132021_dta_2100619_index_0.json"
      }
    ]
  },
  {
    "title": "Lilo & Stitch Cartoon_L6",
    "link_thumb": "https://live.staticflickr.com/65535/51787898785_9d571d7fd4_o.gif",
    "id_album": "685543664",
    "total": 30,
    "size_max_detail_page": 1,
    "list_detail": [
      {
        "index_page": 0,
        "link_page": "https://github.com/lmbstudiocontact/mb4_dt_alb_0/raw/main/14132021_dta_685543664_index_0.json"
      }
    ]
  },
  {
    "title": "Animal Art_L4",
    "link_thumb": "https://live.staticflickr.com/65535/51787791365_29d32ef0e1_o.gif",
    "id_album": "97007464",
    "total": 7,
    "size_max_detail_page": 1,
    "list_detail": [
      {
        "index_page": 0,
        "link_page": "https://github.com/lmbstudiocontact/mb4_dt_alb_0/raw/main/14132021_dta_97007464_index_0.json"
      }
    ]
  },
  {
    "title": "Fox Art_L4",
    "link_thumb": "https://live.staticflickr.com/65535/51787584254_c7ce8080fa_o.gif",
    "id_album": "-646110859",
    "total": 7,
    "size_max_detail_page": 1,
    "list_detail": [
      {
        "index_page": 0,
        "link_page": "https://github.com/lmbstudiocontact/mb4_dt_alb_0/raw/main/14132021_dta_-646110859_index_0.json"
      }
    ]
  },
  {
    "title": "Star War_L2",
    "link_thumb": "https://live.staticflickr.com/65535/51787133276_ef9f796451_o.gif",
    "id_album": "-1637191765",
    "total": 2,
    "size_max_detail_page": 1,
    "list_detail": [
      {
        "index_page": 0,
        "link_page": "https://github.com/lmbstudiocontact/mb4_dt_alb_0/raw/main/14132021_dta_-1637191765_index_0.json"
      }
    ]
  },
  {
    "title": "One Punch Man Anime_L9",
    "link_thumb": "https://live.staticflickr.com/65535/51787319353_48959dbd1f_o.gif",
    "id_album": "-1626855606",
    "total": 2,
    "size_max_detail_page": 1,
    "list_detail": [
      {
        "index_page": 0,
        "link_page": "https://github.com/lmbstudiocontact/mb4_dt_alb_0/raw/main/14132021_dta_-1626855606_index_0.json"
      }
    ]
  },
  {
    "title": "Ragnarok_L10",
    "link_thumb": "https://live.staticflickr.com/65535/51787981300_8896d25975_o.gif",
    "id_album": "-1898619025",
    "total": 15,
    "size_max_detail_page": 1,
    "list_detail": [
      {
        "index_page": 0,
        "link_page": "https://github.com/lmbstudiocontact/mb4_dt_alb_0/raw/main/14132021_dta_-1898619025_index_0.json"
      }
    ]
  },
  {
    "title": "Oggy and the Cockroaches Cartoon_Animation",
    "link_thumb": "https://live.staticflickr.com/65535/51787512084_e6f05ab650_o.gif",
    "id_album": "-297467448",
    "total": 2,
    "size_max_detail_page": 1,
    "list_detail": [
      {
        "index_page": 0,
        "link_page": "https://github.com/lmbstudiocontact/mb4_dt_alb_0/raw/main/14132021_dta_-297467448_index_0.json"
      }
    ]
  },
  {
    "title": "Couple_L10",
    "link_thumb": "https://live.staticflickr.com/65535/51786915356_b538cc8f8b_o.gif",
    "id_album": "-1785780596",
    "total": 24,
    "size_max_detail_page": 1,
    "list_detail": [
      {
        "index_page": 0,
        "link_page": "https://github.com/lmbstudiocontact/mb4_dt_alb_0/raw/main/14132021_dta_-1785780596_index_0.json"
      }
    ]
  },
  {
    "title": "People_Animation",
    "link_thumb": "https://live.staticflickr.com/65535/51786899646_d622ba8004_o.gif",
    "id_album": "-1741814316",
    "total": 2,
    "size_max_detail_page": 1,
    "list_detail": [
      {
        "index_page": 0,
        "link_page": "https://github.com/lmbstudiocontact/mb4_dt_alb_0/raw/main/14132021_dta_-1741814316_index_0.json"
      }
    ]
  },
  {
    "title": "Kitty & My Melody_L10",
    "link_thumb": "https://live.staticflickr.com/65535/51787887445_e43689490f_o.gif",
    "id_album": "1152005041",
    "total": 76,
    "size_max_detail_page": 2,
    "list_detail": [
      {
        "index_page": 0,
        "link_page": "https://github.com/lmbstudiocontact/mb4_dt_alb_0/raw/main/14132021_dta_1152005041_index_0.json"
      },
      {
        "index_page": 1,
        "link_page": "https://github.com/lmbstudiocontact/mb4_dt_alb_0/raw/main/14132021_dta_1152005041_index_1.json"
      }
    ]
  },
  {
    "title": "Naruto Anime_L2",
    "link_thumb": "https://live.staticflickr.com/65535/51787052286_0ae09fd852_o.gif",
    "id_album": "1894397984",
    "total": 37,
    "size_max_detail_page": 1,
    "list_detail": [
      {
        "index_page": 0,
        "link_page": "https://github.com/lmbstudiocontact/mb4_dt_alb_0/raw/main/14132021_dta_1894397984_index_0.json"
      }
    ]
  },
  {
    "title": "Angry Birds_L9",
    "link_thumb": "https://live.staticflickr.com/65535/51787163968_51133395cf_o.gif",
    "id_album": "2112729297",
    "total": 26,
    "size_max_detail_page": 1,
    "list_detail": [
      {
        "index_page": 0,
        "link_page": "https://github.com/lmbstudiocontact/mb4_dt_alb_0/raw/main/14132021_dta_2112729297_index_0.json"
      }
    ]
  },
  {
    "title": "Doraemon Anime_L1",
    "link_thumb": "https://live.staticflickr.com/65535/51787559999_8950d2fcb7_o.gif",
    "id_album": "405661391",
    "total": 16,
    "size_max_detail_page": 1,
    "list_detail": [
      {
        "index_page": 0,
        "link_page": "https://github.com/lmbstudiocontact/mb4_dt_alb_0/raw/main/14132021_dta_405661391_index_0.json"
      }
    ]
  },
  {
    "title": "Rio 2_L2",
    "link_thumb": "https://live.staticflickr.com/65535/51787365213_0be6b2db5f_o.gif",
    "id_album": "-1210862917",
    "total": 17,
    "size_max_detail_page": 1,
    "list_detail": [
      {
        "index_page": 0,
        "link_page": "https://github.com/lmbstudiocontact/mb4_dt_alb_0/raw/main/14132021_dta_-1210862917_index_0.json"
      }
    ]
  },
  {
    "title": "Smurf Houses Cartoon_L8",
    "link_thumb": "https://live.staticflickr.com/65535/51787757669_14213456a6_o.gif",
    "id_album": "228264857",
    "total": 4,
    "size_max_detail_page": 1,
    "list_detail": [
      {
        "index_page": 0,
        "link_page": "https://github.com/lmbstudiocontact/mb4_dt_alb_0/raw/main/14132021_dta_228264857_index_0.json"
      }
    ]
  },
  {
    "title": "Ragnarok_L9",
    "link_thumb": "https://live.staticflickr.com/65535/51787981620_bea1e3f915_o.gif",
    "id_album": "1601322217",
    "total": 15,
    "size_max_detail_page": 1,
    "list_detail": [
      {
        "index_page": 0,
        "link_page": "https://github.com/lmbstudiocontact/mb4_dt_alb_0/raw/main/14132021_dta_1601322217_index_0.json"
      }
    ]
  },
  {
    "title": "Madagascar Cartoon_L7",
    "link_thumb": "https://live.staticflickr.com/65535/51787014941_01088bab4e_o.gif",
    "id_album": "-2014542384",
    "total": 9,
    "size_max_detail_page": 1,
    "list_detail": [
      {
        "index_page": 0,
        "link_page": "https://github.com/lmbstudiocontact/mb4_dt_alb_0/raw/main/14132021_dta_-2014542384_index_0.json"
      }
    ]
  },
  {
    "title": "Naruto Anime_L1",
    "link_thumb": "https://live.staticflickr.com/65535/51786237567_60cca9ce90_o.gif",
    "id_album": "1894397983",
    "total": 37,
    "size_max_detail_page": 1,
    "list_detail": [
      {
        "index_page": 0,
        "link_page": "https://github.com/lmbstudiocontact/mb4_dt_alb_0/raw/main/14132021_dta_1894397983_index_0.json"
      }
    ]
  },
  {
    "title": "Butterfly_L7",
    "link_thumb": "https://live.staticflickr.com/65535/51786105167_4e9b202d03_o.gif",
    "id_album": "657564375",
    "total": 6,
    "size_max_detail_page": 1,
    "list_detail": [
      {
        "index_page": 0,
        "link_page": "https://github.com/lmbstudiocontact/mb4_dt_alb_0/raw/main/14132021_dta_657564375_index_0.json"
      }
    ]
  },
  {
    "title": "Boku No Hero Academia Anime_L2",
    "link_thumb": "https://live.staticflickr.com/65535/51786907191_6e38af263e_o.gif",
    "id_album": "197312540",
    "total": 19,
    "size_max_detail_page": 1,
    "list_detail": [
      {
        "index_page": 0,
        "link_page": "https://github.com/lmbstudiocontact/mb4_dt_alb_0/raw/main/14132021_dta_197312540_index_0.json"
      }
    ]
  },
  {
    "title": "Simpsons Cartoon_L1",
    "link_thumb": "https://live.staticflickr.com/65535/51788021565_79e4a923e0_o.gif",
    "id_album": "1276946588",
    "total": 8,
    "size_max_detail_page": 1,
    "list_detail": [
      {
        "index_page": 0,
        "link_page": "https://github.com/lmbstudiocontact/mb4_dt_alb_0/raw/main/14132021_dta_1276946588_index_0.json"
      }
    ]
  },
  {
    "title": "Finn Mertens Cartoon_Animation",
    "link_thumb": "https://live.staticflickr.com/65535/51787788475_3e30f13225_o.gif",
    "id_album": "665929798",
    "total": 1,
    "size_max_detail_page": 1,
    "list_detail": [
      {
        "index_page": 0,
        "link_page": "https://github.com/lmbstudiocontact/mb4_dt_alb_0/raw/main/14132021_dta_665929798_index_0.json"
      }
    ]
  },
  {
    "title": "Wolf_L3",
    "link_thumb": "https://live.staticflickr.com/65535/51787753414_336ca6e3ac_o.gif",
    "id_album": "-1110849964",
    "total": 5,
    "size_max_detail_page": 1,
    "list_detail": [
      {
        "index_page": 0,
        "link_page": "https://github.com/lmbstudiocontact/mb4_dt_alb_0/raw/main/14132021_dta_-1110849964_index_0.json"
      }
    ]
  },
  {
    "title": "People",
    "link_thumb": "https://live.staticflickr.com/65535/51787522794_a7db398457_o.gif",
    "id_album": "-1907941713",
    "total": 29,
    "size_max_detail_page": 1,
    "list_detail": [
      {
        "index_page": 0,
        "link_page": "https://github.com/lmbstudiocontact/mb4_dt_alb_0/raw/main/14132021_dta_-1907941713_index_0.json"
      }
    ]
  },
  {
    "title": "Mickey Cartoon_L10",
    "link_thumb": "https://live.staticflickr.com/65535/51787017491_65bc71a3af_o.gif",
    "id_album": "569836978",
    "total": 22,
    "size_max_detail_page": 1,
    "list_detail": [
      {
        "index_page": 0,
        "link_page": "https://github.com/lmbstudiocontact/mb4_dt_alb_0/raw/main/14132021_dta_569836978_index_0.json"
      }
    ]
  },
  {
    "title": "Frozen Cartoon_L7",
    "link_thumb": "https://live.staticflickr.com/65535/51786970916_bcaa84f050_o.gif",
    "id_album": "995274076",
    "total": 11,
    "size_max_detail_page": 1,
    "list_detail": [
      {
        "index_page": 0,
        "link_page": "https://github.com/lmbstudiocontact/mb4_dt_alb_0/raw/main/14132021_dta_995274076_index_0.json"
      }
    ]
  },
  {
    "title": "Naruto Anime_L10",
    "link_thumb": "https://live.staticflickr.com/65535/51787667149_149ab7ae77_o.gif",
    "id_album": "-1403204623",
    "total": 37,
    "size_max_detail_page": 1,
    "list_detail": [
      {
        "index_page": 0,
        "link_page": "https://github.com/lmbstudiocontact/mb4_dt_alb_0/raw/main/14132021_dta_-1403204623_index_0.json"
      }
    ]
  },
  {
    "title": "Simpsons Cartoon_L3",
    "link_thumb": "https://live.staticflickr.com/65535/51787147396_14c9361a43_o.gif",
    "id_album": "1276946590",
    "total": 8,
    "size_max_detail_page": 1,
    "list_detail": [
      {
        "index_page": 0,
        "link_page": "https://github.com/lmbstudiocontact/mb4_dt_alb_0/raw/main/14132021_dta_1276946590_index_0.json"
      }
    ]
  },
  {
    "title": "Dragon Ball Anime_L5",
    "link_thumb": "https://live.staticflickr.com/65535/51787192748_371efe19c3_o.gif",
    "id_album": "1464725224",
    "total": 60,
    "size_max_detail_page": 2,
    "list_detail": [
      {
        "index_page": 0,
        "link_page": "https://github.com/lmbstudiocontact/mb4_dt_alb_0/raw/main/14132021_dta_1464725224_index_0.json"
      },
      {
        "index_page": 1,
        "link_page": "https://github.com/lmbstudiocontact/mb4_dt_alb_0/raw/main/14132021_dta_1464725224_index_1.json"
      }
    ]
  },
  {
    "title": "Madagascar Cartoon_L3",
    "link_thumb": "https://live.staticflickr.com/65535/51787637679_d54ec8f0c7_o.gif",
    "id_album": "-2014542388",
    "total": 9,
    "size_max_detail_page": 1,
    "list_detail": [
      {
        "index_page": 0,
        "link_page": "https://github.com/lmbstudiocontact/mb4_dt_alb_0/raw/main/14132021_dta_-2014542388_index_0.json"
      }
    ]
  },
  {
    "title": "Halloween Ghost Witch_L10",
    "link_thumb": "https://live.staticflickr.com/65535/51787850950_cffd47f597_o.gif",
    "id_album": "-1690866577",
    "total": 49,
    "size_max_detail_page": 1,
    "list_detail": [
      {
        "index_page": 0,
        "link_page": "https://github.com/lmbstudiocontact/mb4_dt_alb_0/raw/main/14132021_dta_-1690866577_index_0.json"
      }
    ]
  },
  {
    "title": "Doraemon Anime_L8",
    "link_thumb": "https://live.staticflickr.com/65535/51787205503_9aaa47e2fa_o.gif",
    "id_album": "405661398",
    "total": 16,
    "size_max_detail_page": 1,
    "list_detail": [
      {
        "index_page": 0,
        "link_page": "https://github.com/lmbstudiocontact/mb4_dt_alb_0/raw/main/14132021_dta_405661398_index_0.json"
      }
    ]
  },
  {
    "title": "Wolf_L2",
    "link_thumb": "https://live.staticflickr.com/65535/51787126521_aa070a51a1_o.gif",
    "id_album": "-1110849965",
    "total": 5,
    "size_max_detail_page": 1,
    "list_detail": [
      {
        "index_page": 0,
        "link_page": "https://github.com/lmbstudiocontact/mb4_dt_alb_0/raw/main/14132021_dta_-1110849965_index_0.json"
      }
    ]
  },
  {
    "title": "Dragon Art_L2",
    "link_thumb": "https://live.staticflickr.com/65535/51787567314_cca7762303_o.gif",
    "id_album": "2059013999",
    "total": 13,
    "size_max_detail_page": 1,
    "list_detail": [
      {
        "index_page": 0,
        "link_page": "https://github.com/lmbstudiocontact/mb4_dt_alb_0/raw/main/14132021_dta_2059013999_index_0.json"
      }
    ]
  },
  {
    "title": "Wolf_L10",
    "link_thumb": "https://live.staticflickr.com/65535/51788000395_3ba672551b_o.gif",
    "id_album": "-76610530",
    "total": 5,
    "size_max_detail_page": 1,
    "list_detail": [
      {
        "index_page": 0,
        "link_page": "https://github.com/lmbstudiocontact/mb4_dt_alb_0/raw/main/14132021_dta_-76610530_index_0.json"
      }
    ]
  },
  {
    "title": "Dragon Art_L8",
    "link_thumb": "https://live.staticflickr.com/65535/51787813175_a45cd14d82_o.gif",
    "id_album": "2059014005",
    "total": 13,
    "size_max_detail_page": 1,
    "list_detail": [
      {
        "index_page": 0,
        "link_page": "https://github.com/lmbstudiocontact/mb4_dt_alb_0/raw/main/14132021_dta_2059014005_index_0.json"
      }
    ]
  },
  {
    "title": "Monsters University Cartoon_Animation",
    "link_thumb": "https://live.staticflickr.com/65535/51787509164_6c4e9c2ce8_o.gif",
    "id_album": "-1611324024",
    "total": 1,
    "size_max_detail_page": 1,
    "list_detail": [
      {
        "index_page": 0,
        "link_page": "https://github.com/lmbstudiocontact/mb4_dt_alb_0/raw/main/14132021_dta_-1611324024_index_0.json"
      }
    ]
  },
  {
    "title": "Lilo & Stitch Cartoon_L8",
    "link_thumb": "https://live.staticflickr.com/65535/51787274868_e7b089617f_o.gif",
    "id_album": "685543666",
    "total": 30,
    "size_max_detail_page": 1,
    "list_detail": [
      {
        "index_page": 0,
        "link_page": "https://github.com/lmbstudiocontact/mb4_dt_alb_0/raw/main/14132021_dta_685543666_index_0.json"
      }
    ]
  },
  {
    "title": "Star War_L9",
    "link_thumb": "https://live.staticflickr.com/65535/51787754149_2a969e7007_o.gif",
    "id_album": "-1637191758",
    "total": 2,
    "size_max_detail_page": 1,
    "list_detail": [
      {
        "index_page": 0,
        "link_page": "https://github.com/lmbstudiocontact/mb4_dt_alb_0/raw/main/14132021_dta_-1637191758_index_0.json"
      }
    ]
  },
  {
    "title": "SpongeBob SquarePants Cartoon_Animation",
    "link_thumb": "https://live.staticflickr.com/65535/51787764775_e16fe8b6fd_o.gif",
    "id_album": "-1216979603",
    "total": 2,
    "size_max_detail_page": 1,
    "list_detail": [
      {
        "index_page": 0,
        "link_page": "https://github.com/lmbstudiocontact/mb4_dt_alb_0/raw/main/14132021_dta_-1216979603_index_0.json"
      }
    ]
  },
  {
    "title": "Animal Art_L6",
    "link_thumb": "https://live.staticflickr.com/65535/51787790780_717a9fb6bb_o.gif",
    "id_album": "97007466",
    "total": 7,
    "size_max_detail_page": 1,
    "list_detail": [
      {
        "index_page": 0,
        "link_page": "https://github.com/lmbstudiocontact/mb4_dt_alb_0/raw/main/14132021_dta_97007466_index_0.json"
      }
    ]
  },
  {
    "title": "Boss Baby Cartoon_L5",
    "link_thumb": "https://live.staticflickr.com/65535/51787778415_14db8bd225_o.gif",
    "id_album": "158762705",
    "total": 16,
    "size_max_detail_page": 1,
    "list_detail": [
      {
        "index_page": 0,
        "link_page": "https://github.com/lmbstudiocontact/mb4_dt_alb_0/raw/main/14132021_dta_158762705_index_0.json"
      }
    ]
  }
]