[
  {
    "title": "Mickey Cartoon_L3",
    "link_thumb": "https://live.staticflickr.com/65535/51681540748_b2f65553ff_o.gif",
    "id_album": "1680949824",
    "total": 22,
    "size_max_detail_page": 1,
    "list_detail": [
      {
        "index_page": 0,
        "link_page": "https://github.com/lmbstudiocontact/mb4_dt_alb_0/raw/main/14132021_dta_1680949824_index_0.json"
      }
    ]
  },
  {
    "title": "Panda Art_L9",
    "link_thumb": "https://live.staticflickr.com/65535/51685002977_4f248415cb_o.gif",
    "id_album": "586574351",
    "total": 5,
    "size_max_detail_page": 1,
    "list_detail": [
      {
        "index_page": 0,
        "link_page": "https://github.com/lmbstudiocontact/mb4_dt_alb_0/raw/main/14132021_dta_586574351_index_0.json"
      }
    ]
  },
  {
    "title": "Simpsons Cartoon_L3",
    "link_thumb": "https://live.staticflickr.com/65535/51689871910_2e841670ff_o.gif",
    "id_album": "1276946590",
    "total": 8,
    "size_max_detail_page": 1,
    "list_detail": [
      {
        "index_page": 0,
        "link_page": "https://github.com/lmbstudiocontact/mb4_dt_alb_0/raw/main/14132021_dta_1276946590_index_0.json"
      }
    ]
  },
  {
    "title": "Buddhist Terms_L9",
    "link_thumb": "https://live.staticflickr.com/65535/51674232120_5a54bc1f9f_o.gif",
    "id_album": "518853936",
    "total": 13,
    "size_max_detail_page": 1,
    "list_detail": [
      {
        "index_page": 0,
        "link_page": "https://github.com/lmbstudiocontact/mb4_dt_alb_0/raw/main/14132021_dta_518853936_index_0.json"
      }
    ]
  },
  {
    "title": "Simpsons Cartoon_L5",
    "link_thumb": "https://live.staticflickr.com/65535/51689896305_b3e0a69a30_o.gif",
    "id_album": "1276946592",
    "total": 8,
    "size_max_detail_page": 1,
    "list_detail": [
      {
        "index_page": 0,
        "link_page": "https://github.com/lmbstudiocontact/mb4_dt_alb_0/raw/main/14132021_dta_1276946592_index_0.json"
      }
    ]
  },
  {
    "title": "Sonic Cartoon_Animation",
    "link_thumb": "https://live.staticflickr.com/65535/51670427762_c1f2182c14_o.gif",
    "id_album": "-172787041",
    "total": 3,
    "size_max_detail_page": 1,
    "list_detail": [
      {
        "index_page": 0,
        "link_page": "https://github.com/lmbstudiocontact/mb4_dt_alb_0/raw/main/14132021_dta_-172787041_index_0.json"
      }
    ]
  },
  {
    "title": "Dragon Art_L5",
    "link_thumb": "https://live.staticflickr.com/65535/51675969623_e62d200a55_o.gif",
    "id_album": "2059014002",
    "total": 13,
    "size_max_detail_page": 1,
    "list_detail": [
      {
        "index_page": 0,
        "link_page": "https://github.com/lmbstudiocontact/mb4_dt_alb_0/raw/main/14132021_dta_2059014002_index_0.json"
      }
    ]
  },
  {
    "title": "Horror Art_L7",
    "link_thumb": "https://live.staticflickr.com/65535/51679602673_729f148ef4_o.gif",
    "id_album": "529377277",
    "total": 41,
    "size_max_detail_page": 1,
    "list_detail": [
      {
        "index_page": 0,
        "link_page": "https://github.com/lmbstudiocontact/mb4_dt_alb_0/raw/main/14132021_dta_529377277_index_0.json"
      }
    ]
  },
  {
    "title": "Pokmon Anime_L1",
    "link_thumb": "https://live.staticflickr.com/65535/51686807879_743d60e9c8_o.gif",
    "id_album": "-555824144",
    "total": 108,
    "size_max_detail_page": 3,
    "list_detail": [
      {
        "index_page": 0,
        "link_page": "https://github.com/lmbstudiocontact/mb4_dt_alb_0/raw/main/14132021_dta_-555824144_index_0.json"
      },
      {
        "index_page": 1,
        "link_page": "https://github.com/lmbstudiocontact/mb4_dt_alb_0/raw/main/14132021_dta_-555824144_index_1.json"
      },
      {
        "index_page": 2,
        "link_page": "https://github.com/lmbstudiocontact/mb4_dt_alb_0/raw/main/14132021_dta_-555824144_index_2.json"
      }
    ]
  },
  {
    "title": "Disney Cartoon_L6",
    "link_thumb": "https://live.staticflickr.com/65535/51676037529_a4945649bb_o.gif",
    "id_album": "-779586265",
    "total": 54,
    "size_max_detail_page": 2,
    "list_detail": [
      {
        "index_page": 0,
        "link_page": "https://github.com/lmbstudiocontact/mb4_dt_alb_0/raw/main/14132021_dta_-779586265_index_0.json"
      },
      {
        "index_page": 1,
        "link_page": "https://github.com/lmbstudiocontact/mb4_dt_alb_0/raw/main/14132021_dta_-779586265_index_1.json"
      }
    ]
  },
  {
    "title": "Death Note Anime_L10",
    "link_thumb": "https://live.staticflickr.com/65535/51675679440_92764cbe05_o.gif",
    "id_album": "1287300542",
    "total": 8,
    "size_max_detail_page": 1,
    "list_detail": [
      {
        "index_page": 0,
        "link_page": "https://github.com/lmbstudiocontact/mb4_dt_alb_0/raw/main/14132021_dta_1287300542_index_0.json"
      }
    ]
  },
  {
    "title": "Spider Man Cartoon_L2",
    "link_thumb": "https://live.staticflickr.com/65535/51690060325_b21b442fe0_o.gif",
    "id_album": "1735002392",
    "total": 16,
    "size_max_detail_page": 1,
    "list_detail": [
      {
        "index_page": 0,
        "link_page": "https://github.com/lmbstudiocontact/mb4_dt_alb_0/raw/main/14132021_dta_1735002392_index_0.json"
      }
    ]
  },
  {
    "title": "Angry Birds_L2",
    "link_thumb": "https://live.staticflickr.com/65535/51673456385_8a8628cbb8_o.gif",
    "id_album": "2112729290",
    "total": 26,
    "size_max_detail_page": 1,
    "list_detail": [
      {
        "index_page": 0,
        "link_page": "https://github.com/lmbstudiocontact/mb4_dt_alb_0/raw/main/14132021_dta_2112729290_index_0.json"
      }
    ]
  },
  {
    "title": "Pokmon Anime_L3",
    "link_thumb": "https://live.staticflickr.com/65535/51686620191_65f0d3f9e4_o.gif",
    "id_album": "-555824142",
    "total": 108,
    "size_max_detail_page": 3,
    "list_detail": [
      {
        "index_page": 0,
        "link_page": "https://github.com/lmbstudiocontact/mb4_dt_alb_0/raw/main/14132021_dta_-555824142_index_0.json"
      },
      {
        "index_page": 1,
        "link_page": "https://github.com/lmbstudiocontact/mb4_dt_alb_0/raw/main/14132021_dta_-555824142_index_1.json"
      },
      {
        "index_page": 2,
        "link_page": "https://github.com/lmbstudiocontact/mb4_dt_alb_0/raw/main/14132021_dta_-555824142_index_2.json"
      }
    ]
  },
  {
    "title": "One Punch Man Anime_L6",
    "link_thumb": "https://live.staticflickr.com/65535/51686438460_1173a7338b_o.gif",
    "id_album": "-1626855609",
    "total": 2,
    "size_max_detail_page": 1,
    "list_detail": [
      {
        "index_page": 0,
        "link_page": "https://github.com/lmbstudiocontact/mb4_dt_alb_0/raw/main/14132021_dta_-1626855609_index_0.json"
      }
    ]
  },
  {
    "title": "Dragon Ball Anime_L4",
    "link_thumb": "https://live.staticflickr.com/65535/51676662574_a37d69132b_o.gif",
    "id_album": "1464725223",
    "total": 60,
    "size_max_detail_page": 2,
    "list_detail": [
      {
        "index_page": 0,
        "link_page": "https://github.com/lmbstudiocontact/mb4_dt_alb_0/raw/main/14132021_dta_1464725223_index_0.json"
      },
      {
        "index_page": 1,
        "link_page": "https://github.com/lmbstudiocontact/mb4_dt_alb_0/raw/main/14132021_dta_1464725223_index_1.json"
      }
    ]
  },
  {
    "title": "Animal Art_L1",
    "link_thumb": "https://live.staticflickr.com/65535/51672056147_888882e684_o.gif",
    "id_album": "97007461",
    "total": 7,
    "size_max_detail_page": 1,
    "list_detail": [
      {
        "index_page": 0,
        "link_page": "https://github.com/lmbstudiocontact/mb4_dt_alb_0/raw/main/14132021_dta_97007461_index_0.json"
      }
    ]
  },
  {
    "title": "Onmyoji_L4",
    "link_thumb": "https://live.staticflickr.com/65535/51685905193_85a87dc29a_o.gif",
    "id_album": "389318916",
    "total": 26,
    "size_max_detail_page": 1,
    "list_detail": [
      {
        "index_page": 0,
        "link_page": "https://github.com/lmbstudiocontact/mb4_dt_alb_0/raw/main/14132021_dta_389318916_index_0.json"
      }
    ]
  },
  {
    "title": "One Piece Anime_L4",
    "link_thumb": "https://live.staticflickr.com/65535/51683824067_9252ceb4dc_o.gif",
    "id_album": "1351456607",
    "total": 135,
    "size_max_detail_page": 3,
    "list_detail": [
      {
        "index_page": 0,
        "link_page": "https://github.com/lmbstudiocontact/mb4_dt_alb_0/raw/main/14132021_dta_1351456607_index_0.json"
      },
      {
        "index_page": 1,
        "link_page": "https://github.com/lmbstudiocontact/mb4_dt_alb_0/raw/main/14132021_dta_1351456607_index_1.json"
      },
      {
        "index_page": 2,
        "link_page": "https://github.com/lmbstudiocontact/mb4_dt_alb_0/raw/main/14132021_dta_1351456607_index_2.json"
      }
    ]
  },
  {
    "title": "Cartoon",
    "link_thumb": "https://live.staticflickr.com/65535/51698198575_0faee83e8e_o.gif",
    "id_album": "-2075887794",
    "total": 299,
    "size_max_detail_page": 6,
    "list_detail": [
      {
        "index_page": 0,
        "link_page": "https://github.com/lmbstudiocontact/mb4_dt_alb_0/raw/main/14132021_dta_-2075887794_index_0.json"
      },
      {
        "index_page": 1,
        "link_page": "https://github.com/lmbstudiocontact/mb4_dt_alb_0/raw/main/14132021_dta_-2075887794_index_1.json"
      },
      {
        "index_page": 2,
        "link_page": "https://github.com/lmbstudiocontact/mb4_dt_alb_0/raw/main/14132021_dta_-2075887794_index_2.json"
      },
      {
        "index_page": 3,
        "link_page": "https://github.com/lmbstudiocontact/mb4_dt_alb_0/raw/main/14132021_dta_-2075887794_index_3.json"
      },
      {
        "index_page": 4,
        "link_page": "https://github.com/lmbstudiocontact/mb4_dt_alb_0/raw/main/14132021_dta_-2075887794_index_4.json"
      },
      {
        "index_page": 5,
        "link_page": "https://github.com/lmbstudiocontact/mb4_dt_alb_0/raw/main/14132021_dta_-2075887794_index_5.json"
      }
    ]
  },
  {
    "title": "Spider Man Cartoon_L1",
    "link_thumb": "https://live.staticflickr.com/65535/51688350537_63e1a5db03_o.gif",
    "id_album": "1735002391",
    "total": 16,
    "size_max_detail_page": 1,
    "list_detail": [
      {
        "index_page": 0,
        "link_page": "https://github.com/lmbstudiocontact/mb4_dt_alb_0/raw/main/14132021_dta_1735002391_index_0.json"
      }
    ]
  },
  {
    "title": "Seven deadly sins Anime_L9",
    "link_thumb": "https://live.staticflickr.com/65535/51688387576_b87b56e182_o.gif",
    "id_album": "1802210945",
    "total": 43,
    "size_max_detail_page": 1,
    "list_detail": [
      {
        "index_page": 0,
        "link_page": "https://github.com/lmbstudiocontact/mb4_dt_alb_0/raw/main/14132021_dta_1802210945_index_0.json"
      }
    ]
  },
  {
    "title": "Panda Art_L7",
    "link_thumb": "https://live.staticflickr.com/65535/51686684755_efee2b1088_o.gif",
    "id_album": "586574349",
    "total": 5,
    "size_max_detail_page": 1,
    "list_detail": [
      {
        "index_page": 0,
        "link_page": "https://github.com/lmbstudiocontact/mb4_dt_alb_0/raw/main/14132021_dta_586574349_index_0.json"
      }
    ]
  },
  {
    "title": "Shiv_L7",
    "link_thumb": "https://live.staticflickr.com/65535/51689081158_913f561336_o.gif",
    "id_album": "-568595352",
    "total": 32,
    "size_max_detail_page": 1,
    "list_detail": [
      {
        "index_page": 0,
        "link_page": "https://github.com/lmbstudiocontact/mb4_dt_alb_0/raw/main/14132021_dta_-568595352_index_0.json"
      }
    ]
  },
  {
    "title": "Onmyoji_L9",
    "link_thumb": "https://live.staticflickr.com/65535/51686638150_298969ecaf_o.gif",
    "id_album": "389318921",
    "total": 26,
    "size_max_detail_page": 1,
    "list_detail": [
      {
        "index_page": 0,
        "link_page": "https://github.com/lmbstudiocontact/mb4_dt_alb_0/raw/main/14132021_dta_389318921_index_0.json"
      }
    ]
  },
  {
    "title": "Frozen Cartoon_L8",
    "link_thumb": "https://live.staticflickr.com/65535/51679094700_630ca0348d_o.gif",
    "id_album": "995274077",
    "total": 11,
    "size_max_detail_page": 1,
    "list_detail": [
      {
        "index_page": 0,
        "link_page": "https://github.com/lmbstudiocontact/mb4_dt_alb_0/raw/main/14132021_dta_995274077_index_0.json"
      }
    ]
  },
  {
    "title": "Animal Art_L3",
    "link_thumb": "https://live.staticflickr.com/65535/51672071662_4ec90bd5f3_o.gif",
    "id_album": "97007463",
    "total": 7,
    "size_max_detail_page": 1,
    "list_detail": [
      {
        "index_page": 0,
        "link_page": "https://github.com/lmbstudiocontact/mb4_dt_alb_0/raw/main/14132021_dta_97007463_index_0.json"
      }
    ]
  },
  {
    "title": "Panda Art_L1",
    "link_thumb": "https://live.staticflickr.com/65535/51686447439_4572cf297f_o.gif",
    "id_album": "586574343",
    "total": 5,
    "size_max_detail_page": 1,
    "list_detail": [
      {
        "index_page": 0,
        "link_page": "https://github.com/lmbstudiocontact/mb4_dt_alb_0/raw/main/14132021_dta_586574343_index_0.json"
      }
    ]
  },
  {
    "title": "Lilo & Stitch Cartoon_L10",
    "link_thumb": "https://live.staticflickr.com/65535/51681514649_b072c2bfbb_o.gif",
    "id_album": "-222983003",
    "total": 30,
    "size_max_detail_page": 1,
    "list_detail": [
      {
        "index_page": 0,
        "link_page": "https://github.com/lmbstudiocontact/mb4_dt_alb_0/raw/main/14132021_dta_-222983003_index_0.json"
      }
    ]
  },
  {
    "title": "Smurf Houses Cartoon_L8",
    "link_thumb": "https://live.staticflickr.com/65535/51689995235_f4f3e1e4a7_o.gif",
    "id_album": "228264857",
    "total": 4,
    "size_max_detail_page": 1,
    "list_detail": [
      {
        "index_page": 0,
        "link_page": "https://github.com/lmbstudiocontact/mb4_dt_alb_0/raw/main/14132021_dta_228264857_index_0.json"
      }
    ]
  },
  {
    "title": "Language Vietnamese_Animation",
    "link_thumb": "https://live.staticflickr.com/65535/51672266298_5da7e55f52_o.gif",
    "id_album": "1624213036",
    "total": 6,
    "size_max_detail_page": 1,
    "list_detail": [
      {
        "index_page": 0,
        "link_page": "https://github.com/lmbstudiocontact/mb4_dt_alb_0/raw/main/14132021_dta_1624213036_index_0.json"
      }
    ]
  },
  {
    "title": "Music_L5",
    "link_thumb": "https://live.staticflickr.com/65535/51682142808_24b268b2f7_o.gif",
    "id_album": "908522979",
    "total": 24,
    "size_max_detail_page": 1,
    "list_detail": [
      {
        "index_page": 0,
        "link_page": "https://github.com/lmbstudiocontact/mb4_dt_alb_0/raw/main/14132021_dta_908522979_index_0.json"
      }
    ]
  },
  {
    "title": "Sports",
    "link_thumb": "https://live.staticflickr.com/65535/51670488997_a8abde7a8f_o.gif",
    "id_album": "-1811893345",
    "total": 78,
    "size_max_detail_page": 2,
    "list_detail": [
      {
        "index_page": 0,
        "link_page": "https://github.com/lmbstudiocontact/mb4_dt_alb_0/raw/main/14132021_dta_-1811893345_index_0.json"
      },
      {
        "index_page": 1,
        "link_page": "https://github.com/lmbstudiocontact/mb4_dt_alb_0/raw/main/14132021_dta_-1811893345_index_1.json"
      }
    ]
  },
  {
    "title": "Ragnarok_L9",
    "link_thumb": "https://live.staticflickr.com/65535/51687838886_9e1eb6f35b_o.gif",
    "id_album": "1601322217",
    "total": 15,
    "size_max_detail_page": 1,
    "list_detail": [
      {
        "index_page": 0,
        "link_page": "https://github.com/lmbstudiocontact/mb4_dt_alb_0/raw/main/14132021_dta_1601322217_index_0.json"
      }
    ]
  },
  {
    "title": "One Piece Anime_L9",
    "link_thumb": "https://live.staticflickr.com/65535/51686278450_ee678fc427_o.gif",
    "id_album": "1351456612",
    "total": 135,
    "size_max_detail_page": 3,
    "list_detail": [
      {
        "index_page": 0,
        "link_page": "https://github.com/lmbstudiocontact/mb4_dt_alb_0/raw/main/14132021_dta_1351456612_index_0.json"
      },
      {
        "index_page": 1,
        "link_page": "https://github.com/lmbstudiocontact/mb4_dt_alb_0/raw/main/14132021_dta_1351456612_index_1.json"
      },
      {
        "index_page": 2,
        "link_page": "https://github.com/lmbstudiocontact/mb4_dt_alb_0/raw/main/14132021_dta_1351456612_index_2.json"
      }
    ]
  },
  {
    "title": "Language Hungarian_Animation",
    "link_thumb": "https://live.staticflickr.com/65535/51672024796_8ba0db9b95_o.gif",
    "id_album": "1515600668",
    "total": 6,
    "size_max_detail_page": 1,
    "list_detail": [
      {
        "index_page": 0,
        "link_page": "https://github.com/lmbstudiocontact/mb4_dt_alb_0/raw/main/14132021_dta_1515600668_index_0.json"
      }
    ]
  },
  {
    "title": "Boku No Hero Academia Anime_L5",
    "link_thumb": "https://live.staticflickr.com/65535/51673689554_bf4b2bd372_o.gif",
    "id_album": "197312543",
    "total": 19,
    "size_max_detail_page": 1,
    "list_detail": [
      {
        "index_page": 0,
        "link_page": "https://github.com/lmbstudiocontact/mb4_dt_alb_0/raw/main/14132021_dta_197312543_index_0.json"
      }
    ]
  },
  {
    "title": "Language Dutch",
    "link_thumb": "https://live.staticflickr.com/65535/51671238406_07d98bd32a_o.gif",
    "id_album": "1548992224",
    "total": 37,
    "size_max_detail_page": 1,
    "list_detail": [
      {
        "index_page": 0,
        "link_page": "https://github.com/lmbstudiocontact/mb4_dt_alb_0/raw/main/14132021_dta_1548992224_index_0.json"
      }
    ]
  },
  {
    "title": "Rio 2_L5",
    "link_thumb": "https://live.staticflickr.com/65535/51688639544_35758da047_o.gif",
    "id_album": "-1210862914",
    "total": 17,
    "size_max_detail_page": 1,
    "list_detail": [
      {
        "index_page": 0,
        "link_page": "https://github.com/lmbstudiocontact/mb4_dt_alb_0/raw/main/14132021_dta_-1210862914_index_0.json"
      }
    ]
  },
  {
    "title": "Frozen Cartoon_L3",
    "link_thumb": "https://live.staticflickr.com/65535/51678182176_aa761ee3ae_o.gif",
    "id_album": "995274072",
    "total": 11,
    "size_max_detail_page": 1,
    "list_detail": [
      {
        "index_page": 0,
        "link_page": "https://github.com/lmbstudiocontact/mb4_dt_alb_0/raw/main/14132021_dta_995274072_index_0.json"
      }
    ]
  },
  {
    "title": "Ghibli Anime_L2",
    "link_thumb": "https://live.staticflickr.com/65535/51678258041_f92d9ec773_o.gif",
    "id_album": "-749595046",
    "total": 17,
    "size_max_detail_page": 1,
    "list_detail": [
      {
        "index_page": 0,
        "link_page": "https://github.com/lmbstudiocontact/mb4_dt_alb_0/raw/main/14132021_dta_-749595046_index_0.json"
      }
    ]
  },
  {
    "title": "Panda Art_L6",
    "link_thumb": "https://live.staticflickr.com/65535/51684994492_eb11f54cbb_o.gif",
    "id_album": "586574348",
    "total": 5,
    "size_max_detail_page": 1,
    "list_detail": [
      {
        "index_page": 0,
        "link_page": "https://github.com/lmbstudiocontact/mb4_dt_alb_0/raw/main/14132021_dta_586574348_index_0.json"
      }
    ]
  },
  {
    "title": "Inside Out Cartoon",
    "link_thumb": "https://live.staticflickr.com/65535/51672286210_faf3422ccc_o.gif",
    "id_album": "2016762456",
    "total": 4,
    "size_max_detail_page": 1,
    "list_detail": [
      {
        "index_page": 0,
        "link_page": "https://github.com/lmbstudiocontact/mb4_dt_alb_0/raw/main/14132021_dta_2016762456_index_0.json"
      }
    ]
  },
  {
    "title": "Cars",
    "link_thumb": "https://live.staticflickr.com/65535/51672092850_0a09870fa4_o.gif",
    "id_album": "2092863",
    "total": 51,
    "size_max_detail_page": 2,
    "list_detail": [
      {
        "index_page": 0,
        "link_page": "https://github.com/lmbstudiocontact/mb4_dt_alb_0/raw/main/14132021_dta_2092863_index_0.json"
      },
      {
        "index_page": 1,
        "link_page": "https://github.com/lmbstudiocontact/mb4_dt_alb_0/raw/main/14132021_dta_2092863_index_1.json"
      }
    ]
  },
  {
    "title": "Joker Harley Quinn_L4",
    "link_thumb": "https://live.staticflickr.com/65535/51680580135_597652b533_o.gif",
    "id_album": "-2022175634",
    "total": 24,
    "size_max_detail_page": 1,
    "list_detail": [
      {
        "index_page": 0,
        "link_page": "https://github.com/lmbstudiocontact/mb4_dt_alb_0/raw/main/14132021_dta_-2022175634_index_0.json"
      }
    ]
  },
  {
    "title": "Buddhist Terms_L2",
    "link_thumb": "https://live.staticflickr.com/65535/51673514478_6ae22d5514_o.gif",
    "id_album": "518853929",
    "total": 13,
    "size_max_detail_page": 1,
    "list_detail": [
      {
        "index_page": 0,
        "link_page": "https://github.com/lmbstudiocontact/mb4_dt_alb_0/raw/main/14132021_dta_518853929_index_0.json"
      }
    ]
  },
  {
    "title": "Couple_L4",
    "link_thumb": "https://live.staticflickr.com/65535/51673513836_b3539aa195_o.gif",
    "id_album": "-888889817",
    "total": 24,
    "size_max_detail_page": 1,
    "list_detail": [
      {
        "index_page": 0,
        "link_page": "https://github.com/lmbstudiocontact/mb4_dt_alb_0/raw/main/14132021_dta_-888889817_index_0.json"
      }
    ]
  },
  {
    "title": "Boss Baby Cartoon_L5",
    "link_thumb": "https://live.staticflickr.com/65535/51672368507_6b9692b2e4_o.gif",
    "id_album": "158762705",
    "total": 16,
    "size_max_detail_page": 1,
    "list_detail": [
      {
        "index_page": 0,
        "link_page": "https://github.com/lmbstudiocontact/mb4_dt_alb_0/raw/main/14132021_dta_158762705_index_0.json"
      }
    ]
  },
  {
    "title": "Dragon Art_L10",
    "link_thumb": "https://live.staticflickr.com/65535/51676546595_582b3297c9_o.gif",
    "id_album": "-595075454",
    "total": 13,
    "size_max_detail_page": 1,
    "list_detail": [
      {
        "index_page": 0,
        "link_page": "https://github.com/lmbstudiocontact/mb4_dt_alb_0/raw/main/14132021_dta_-595075454_index_0.json"
      }
    ]
  },
  {
    "title": "Kung Fu Panda_L2",
    "link_thumb": "https://live.staticflickr.com/65535/51681084758_3f5f975abe_o.gif",
    "id_album": "1222783551",
    "total": 2,
    "size_max_detail_page": 1,
    "list_detail": [
      {
        "index_page": 0,
        "link_page": "https://github.com/lmbstudiocontact/mb4_dt_alb_0/raw/main/14132021_dta_1222783551_index_0.json"
      }
    ]
  }
]